farben/__init__.py
farben/palette.py
farben/palettes/__init__.py
farben/palettes/copic.py
farben/palettes/dulux.py
farben/palettes/hks.py
farben/palettes/ncs.py
farben/palettes/pantone.py
farben/palettes/prismacolor.py
farben/palettes/ral.py
farben/utils.py
farben-2.1.0.dist-info/entry_points.txt
farben-2.1.0.dist-info/LICENSE
farben-2.1.0.dist-info/WHEEL
farben-2.1.0.dist-info/METADATA
farben-2.1.0.dist-info/RECORD
