Metadata-Version: 2.1
Name: farben
Version: 2.1.0
Summary: PANTONE®, RAL®, Dulux®, Copic®, NCS® and Prismacolor® color palettes for Scribus, GIMP, AutoCAD, Inkscape, Krita & LibreOffice
Home-page: https://fundevogel.de
License: MIT
Keywords: autocad,color-palettes,colors,copic,dulux,gimp,inkscape,krita,libreoffice,ncs,palettes,pantone,prismacolor,ral,scribus,swatches
Author: Fundevogel
Author-email: maschinenraum@fundevogel.de
Maintainer: Martin Folkers
Maintainer-email: hello@twobrain.io
Requires-Python: >=3.8,<4.0
Classifier: Development Status :: 5 - Production/Stable
Classifier: Environment :: Console
Classifier: Environment :: Web Environment
Classifier: Intended Audience :: Developers
Classifier: License :: OSI Approved :: MIT License
Classifier: Operating System :: OS Independent
Classifier: Programming Language :: Python :: 3
Classifier: Programming Language :: Python :: 3.8
Classifier: Programming Language :: Python :: 3.9
Classifier: Programming Language :: Python :: 3.10
Classifier: Programming Language :: Python :: 3.10
Classifier: Programming Language :: Python :: 3.11
Classifier: Programming Language :: Python :: 3.8
Classifier: Programming Language :: Python :: 3.9
Classifier: Programming Language :: SQL
Classifier: Topic :: Database
Classifier: Topic :: Internet :: WWW/HTTP
Classifier: Topic :: Software Development :: Libraries :: Python Modules
Requires-Dist: beautifulsoup4 (>=4,<5)
Requires-Dist: click (>=8,<9)
Requires-Dist: lxml (>=4,<5)
Requires-Dist: requests (>=2,<3)
Project-URL: Funding, https://donate.rsf.org
Project-URL: Issue Tracker, https://codeberg.org/Fundevogel/farben/issues
Project-URL: Repository, https://codeberg.org/Fundevogel/farben
